defaultlist-1.2.0.dist-info/METADATA
defaultlist-1.2.0.dist-info/WHEEL
defaultlist-1.2.0.dist-info/entry_points.txt
defaultlist-1.2.0.dist-info/licenses/LICENSE
defaultlist/__init__.py
defaultlist-1.2.0.dist-info/RECORD
