Metadata-Version: 2.1
Name: defaultlist
Version: 1.2.0
Summary: Automatically Extending List
Classifier: Programming Language :: Python :: 3
Classifier: Topic :: Software Development :: Libraries :: Python Modules
Classifier: Development Status :: 5 - Production/Stable
Classifier: Programming Language :: Python :: 3.10
Classifier: Programming Language :: Python :: 3.11
Classifier: Programming Language :: Python :: 3.12
Classifier: Programming Language :: Python :: 3.13
Classifier: Operating System :: OS Independent
Project-URL: Homepage, https://github.com/c0fec0de/defaultlist
Project-URL: Documentation, https://defaultlist.readthedocs.io/en/stable/
Project-URL: Bug Tracker, https://github.com/c0fec0de/defaultlist/issues
Requires-Python: <4.0,>=3.10.0
